sram/sram_8_16_scn4m_subm.v
// OpenRAM SRAM model
// Words: 16
// Word size: 8

`timescale 1ns/1ns

module sram_8_16_scn4m_subm(
// Port 0: RW
    clk0,csb0,web0,addr0,din0,dout0
  );

  parameter DATA_WIDTH = 8 ;
  parameter ADDR_WIDTH = 4 ;
  parameter RAM_DEPTH = 1 << ADDR_WIDTH;
  // FIXME: This delay is arbitrary.
  parameter DELAY = 3 ;

  input  clk0; // clock
  input   csb0; // active low chip select
  input  web0; // active low write control
  input [ADDR_WIDTH-1:0]  addr0;
  input [DATA_WIDTH-1:0]  din0;
  output [DATA_WIDTH-1:0] dout0;

  reg  csb0_reg;
  reg  web0_reg;
  reg [ADDR_WIDTH-1:0]  addr0_reg;
  reg [DATA_WIDTH-1:0]  din0_reg;
  reg [DATA_WIDTH-1:0]  dout0;

  // All inputs are registers
  always @(posedge clk0)
  begin
    csb0_reg = csb0;
    web0_reg = web0;
    addr0_reg = addr0;
    din0_reg = din0;
    dout0 = 8'bx;
    if ( !csb0_reg && web0_reg ) 
      $display($time," Reading %m addr0=%b dout0=%b",addr0_reg,mem[addr0_reg]);
    if ( !csb0_reg && !web0_reg )
      $display($time," Writing %m addr0=%b din0=%b",addr0_reg,din0_reg);
  end

reg [DATA_WIDTH-1:0]    mem [0:RAM_DEPTH-1];

  // Memory Write Block Port 0
  // Write Operation : When web0 = 0, csb0 = 0
  always @ (negedge clk0)
  begin : MEM_WRITE0
    if ( !csb0_reg && !web0_reg )
        mem[addr0_reg] = din0_reg;
  end

  // Memory Read Block Port 0
  // Read Operation : When web0 = 1, csb0 = 0
  always @ (negedge clk0)
  begin : MEM_READ0
    if (!csb0_reg && web0_reg)
       dout0 <= #(DELAY) mem[addr0_reg];
  end

endmodule

sram/build/sram_8_16_scn4m_subm_tb.sv
`timescale 1ns/1ns
module sram_8_16_scn4m_subm_tb;
    reg [7:0] din0;
    wire [7:0] dout0;
    reg [3:0] addr0;
    reg csb0;
    reg web0;
    reg clk0;

    sram_8_16_scn4m_subm #(
        
    ) dut (
        .din0(din0),
        .dout0(dout0),
        .addr0(addr0),
        .csb0(csb0),
        .web0(web0),
        .clk0(clk0)
    );

    initial begin
        $dumpfile("waveforms.vcd");
        $dumpvars(0, dut);
        din0 <= 8'd0;
        #(0*1s);
        addr0 <= 4'd0;
        #(0*1s);
        csb0 <= 1'd0;
        #(0*1s);
        web0 <= 1'd0;
        #(0*1s);
        clk0 <= 1'd0;
        #(0*1s);
        #(2.5e-08*1s);
        web0 <= 1'd1;
        #(0*1s);
        #(2.5e-08*1s);
        din0 <= 8'd217;
        #(0*1s);
        addr0 <= 4'd3;
        #(0*1s);
        web0 <= 1'd0;
        #(0*1s);
        #(1e-09*1s);
        clk0 <= 1'd1;
        #(0*1s);
        #(5e-09*1s);
        din0 <= 8'd0;
        #(0*1s);
        addr0 <= 4'd0;
        #(0*1s);
        web0 <= 1'd1;
        #(0*1s);
        clk0 <= 1'd0;
        #(0*1s);
        #(4e-09*1s);
        din0 <= 8'd144;
        #(0*1s);
        addr0 <= 4'd13;
        #(0*1s);
        web0 <= 1'd0;
        #(0*1s);
        #(1e-09*1s);
        clk0 <= 1'd1;
        #(0*1s);
        #(5e-09*1s);
        din0 <= 8'd0;
        #(0*1s);
        addr0 <= 4'd0;
        #(0*1s);
        web0 <= 1'd1;
        #(0*1s);
        clk0 <= 1'd0;
        #(0*1s);
        #(4e-09*1s);
        din0 <= 8'd125;
        #(0*1s);
        addr0 <= 4'd4;
        #(0*1s);
        web0 <= 1'd0;
        #(0*1s);
        #(1e-09*1s);
        clk0 <= 1'd1;
        #(0*1s);
        #(5e-09*1s);
        din0 <= 8'd0;
        #(0*1s);
        addr0 <= 4'd0;
        #(0*1s);
        web0 <= 1'd1;
        #(0*1s);
        clk0 <= 1'd0;
        #(0*1s);
        #(4e-09*1s);
        din0 <= 8'd155;
        #(0*1s);
        addr0 <= 4'd8;
        #(0*1s);
        web0 <= 1'd0;
        #(0*1s);
        #(1e-09*1s);
        clk0 <= 1'd1;
        #(0*1s);
        #(5e-09*1s);
        din0 <= 8'd0;
        #(0*1s);
        addr0 <= 4'd0;
        #(0*1s);
        web0 <= 1'd1;
        #(0*1s);
        clk0 <= 1'd0;
        #(0*1s);
        #(4e-09*1s);
        din0 <= 8'd201;
        #(0*1s);
        addr0 <= 4'd1;
        #(0*1s);
        web0 <= 1'd0;
        #(0*1s);
        #(1e-09*1s);
        clk0 <= 1'd1;
        #(0*1s);
        #(5e-09*1s);
        din0 <= 8'd0;
        #(0*1s);
        addr0 <= 4'd0;
        #(0*1s);
        web0 <= 1'd1;
        #(0*1s);
        clk0 <= 1'd0;
        #(0*1s);
        #(4e-09*1s);
        din0 <= 8'd88;
        #(0*1s);
        addr0 <= 4'd9;
        #(0*1s);
        web0 <= 1'd0;
        #(0*1s);
        #(1e-09*1s);
        clk0 <= 1'd1;
        #(0*1s);
        #(5e-09*1s);
        din0 <= 8'd0;
        #(0*1s);
        addr0 <= 4'd0;
        #(0*1s);
        web0 <= 1'd1;
        #(0*1s);
        clk0 <= 1'd0;
        #(0*1s);
        #(4e-09*1s);
        din0 <= 8'd121;
        #(0*1s);
        addr0 <= 4'd10;
        #(0*1s);
        web0 <= 1'd0;
        #(0*1s);
        #(1e-09*1s);
        clk0 <= 1'd1;
        #(0*1s);
        #(5e-09*1s);
        din0 <= 8'd0;
        #(0*1s);
        addr0 <= 4'd0;
        #(0*1s);
        web0 <= 1'd1;
        #(0*1s);
        clk0 <= 1'd0;
        #(0*1s);
        #(4e-09*1s);
        din0 <= 8'd197;
        #(0*1s);
        addr0 <= 4'd2;
        #(0*1s);
        web0 <= 1'd0;
        #(0*1s);
        #(1e-09*1s);
        clk0 <= 1'd1;
        #(0*1s);
        #(5e-09*1s);
        din0 <= 8'd0;
        #(0*1s);
        addr0 <= 4'd0;
        #(0*1s);
        web0 <= 1'd1;
        #(0*1s);
        clk0 <= 1'd0;
        #(0*1s);
        #(4e-09*1s);
        din0 <= 8'd98;
        #(0*1s);
        addr0 <= 4'd5;
        #(0*1s);
        web0 <= 1'd0;
        #(0*1s);
        #(1e-09*1s);
        clk0 <= 1'd1;
        #(0*1s);
        #(5e-09*1s);
        din0 <= 8'd0;
        #(0*1s);
        addr0 <= 4'd0;
        #(0*1s);
        web0 <= 1'd1;
        #(0*1s);
        clk0 <= 1'd0;
        #(0*1s);
        #(4e-09*1s);
        din0 <= 8'd208;
        #(0*1s);
        addr0 <= 4'd14;
        #(0*1s);
        web0 <= 1'd0;
        #(0*1s);
        #(1e-09*1s);
        clk0 <= 1'd1;
        #(0*1s);
        #(5e-09*1s);
        din0 <= 8'd0;
        #(0*1s);
        addr0 <= 4'd0;
        #(0*1s);
        web0 <= 1'd1;
        #(0*1s);
        clk0 <= 1'd0;
        #(0*1s);
        #(4e-09*1s);
        din0 <= 8'd228;
        #(0*1s);
        addr0 <= 4'd7;
        #(0*1s);
        web0 <= 1'd0;
        #(0*1s);
        #(1e-09*1s);
        clk0 <= 1'd1;
        #(0*1s);
        #(5e-09*1s);
        din0 <= 8'd0;
        #(0*1s);
        addr0 <= 4'd0;
        #(0*1s);
        web0 <= 1'd1;
        #(0*1s);
        clk0 <= 1'd0;
        #(0*1s);
        #(4e-09*1s);
        din0 <= 8'd43;
        #(0*1s);
        addr0 <= 4'd6;
        #(0*1s);
        web0 <= 1'd0;
        #(0*1s);
        #(1e-09*1s);
        clk0 <= 1'd1;
        #(0*1s);
        #(5e-09*1s);
        din0 <= 8'd0;
        #(0*1s);
        addr0 <= 4'd0;
        #(0*1s);
        web0 <= 1'd1;
        #(0*1s);
        clk0 <= 1'd0;
        #(0*1s);
        #(4e-09*1s);
        din0 <= 8'd64;
        #(0*1s);
        addr0 <= 4'd0;
        #(0*1s);
        web0 <= 1'd0;
        #(0*1s);
        #(1e-09*1s);
        clk0 <= 1'd1;
        #(0*1s);
        #(5e-09*1s);
        din0 <= 8'd0;
        #(0*1s);
        addr0 <= 4'd0;
        #(0*1s);
        web0 <= 1'd1;
        #(0*1s);
        clk0 <= 1'd0;
        #(0*1s);
        #(4e-09*1s);
        din0 <= 8'd119;
        #(0*1s);
        addr0 <= 4'd12;
        #(0*1s);
        web0 <= 1'd0;
        #(0*1s);
        #(1e-09*1s);
        clk0 <= 1'd1;
        #(0*1s);
        #(5e-09*1s);
        din0 <= 8'd0;
        #(0*1s);
        addr0 <= 4'd0;
        #(0*1s);
        web0 <= 1'd1;
        #(0*1s);
        clk0 <= 1'd0;
        #(0*1s);
        #(4e-09*1s);
        din0 <= 8'd248;
        #(0*1s);
        addr0 <= 4'd15;
        #(0*1s);
        web0 <= 1'd0;
        #(0*1s);
        #(1e-09*1s);
        clk0 <= 1'd1;
        #(0*1s);
        #(5e-09*1s);
        din0 <= 8'd0;
        #(0*1s);
        addr0 <= 4'd0;
        #(0*1s);
        web0 <= 1'd1;
        #(0*1s);
        clk0 <= 1'd0;
        #(0*1s);
        #(4e-09*1s);
        din0 <= 8'd249;
        #(0*1s);
        addr0 <= 4'd11;
        #(0*1s);
        web0 <= 1'd0;
        #(0*1s);
        #(1e-09*1s);
        clk0 <= 1'd1;
        #(0*1s);
        #(5e-09*1s);
        din0 <= 8'd0;
        #(0*1s);
        addr0 <= 4'd0;
        #(0*1s);
        web0 <= 1'd1;
        #(0*1s);
        clk0 <= 1'd0;
        #(0*1s);
        #(4e-09*1s);
        addr0 <= 4'd9;
        #(0*1s);
        web0 <= 1'd1;
        #(0*1s);
        #(1e-09*1s);
        clk0 <= 1'd1;
        #(0*1s);
        #(5e-09*1s);
        addr0 <= 4'd0;
        #(0*1s);
        web0 <= 1'd1;
        #(0*1s);
        clk0 <= 1'd0;
        #(0*1s);
        #(4e-09*1s);
        if (!(dout0 === 8'd88)) begin
            $error("Failed on action=193 checking port dout0 with traceback /Users/sgherbst/Dropbox/LaptopSync/Stanford/Research/Code/fault_experiments/sram/sram.py:70.  Expected %x, got %x.", 8'd88, dout0);
        end
        addr0 <= 4'd7;
        #(0*1s);
        web0 <= 1'd1;
        #(0*1s);
        #(1e-09*1s);
        clk0 <= 1'd1;
        #(0*1s);
        #(5e-09*1s);
        addr0 <= 4'd0;
        #(0*1s);
        web0 <= 1'd1;
        #(0*1s);
        clk0 <= 1'd0;
        #(0*1s);
        #(4e-09*1s);
        if (!(dout0 === 8'd228)) begin
            $error("Failed on action=203 checking port dout0 with traceback /Users/sgherbst/Dropbox/LaptopSync/Stanford/Research/Code/fault_experiments/sram/sram.py:70.  Expected %x, got %x.", 8'd228, dout0);
        end
        addr0 <= 4'd15;
        #(0*1s);
        web0 <= 1'd1;
        #(0*1s);
        #(1e-09*1s);
        clk0 <= 1'd1;
        #(0*1s);
        #(5e-09*1s);
        addr0 <= 4'd0;
        #(0*1s);
        web0 <= 1'd1;
        #(0*1s);
        clk0 <= 1'd0;
        #(0*1s);
        #(4e-09*1s);
        if (!(dout0 === 8'd248)) begin
            $error("Failed on action=213 checking port dout0 with traceback /Users/sgherbst/Dropbox/LaptopSync/Stanford/Research/Code/fault_experiments/sram/sram.py:70.  Expected %x, got %x.", 8'd248, dout0);
        end
        addr0 <= 4'd11;
        #(0*1s);
        web0 <= 1'd1;
        #(0*1s);
        #(1e-09*1s);
        clk0 <= 1'd1;
        #(0*1s);
        #(5e-09*1s);
        addr0 <= 4'd0;
        #(0*1s);
        web0 <= 1'd1;
        #(0*1s);
        clk0 <= 1'd0;
        #(0*1s);
        #(4e-09*1s);
        if (!(dout0 === 8'd249)) begin
            $error("Failed on action=223 checking port dout0 with traceback /Users/sgherbst/Dropbox/LaptopSync/Stanford/Research/Code/fault_experiments/sram/sram.py:70.  Expected %x, got %x.", 8'd249, dout0);
        end
        addr0 <= 4'd6;
        #(0*1s);
        web0 <= 1'd1;
        #(0*1s);
        #(1e-09*1s);
        clk0 <= 1'd1;
        #(0*1s);
        #(5e-09*1s);
        addr0 <= 4'd0;
        #(0*1s);
        web0 <= 1'd1;
        #(0*1s);
        clk0 <= 1'd0;
        #(0*1s);
        #(4e-09*1s);
        if (!(dout0 === 8'd43)) begin
            $error("Failed on action=233 checking port dout0 with traceback /Users/sgherbst/Dropbox/LaptopSync/Stanford/Research/Code/fault_experiments/sram/sram.py:70.  Expected %x, got %x.", 8'd43, dout0);
        end
        addr0 <= 4'd2;
        #(0*1s);
        web0 <= 1'd1;
        #(0*1s);
        #(1e-09*1s);
        clk0 <= 1'd1;
        #(0*1s);
        #(5e-09*1s);
        addr0 <= 4'd0;
        #(0*1s);
        web0 <= 1'd1;
        #(0*1s);
        clk0 <= 1'd0;
        #(0*1s);
        #(4e-09*1s);
        if (!(dout0 === 8'd197)) begin
            $error("Failed on action=243 checking port dout0 with traceback /Users/sgherbst/Dropbox/LaptopSync/Stanford/Research/Code/fault_experiments/sram/sram.py:70.  Expected %x, got %x.", 8'd197, dout0);
        end
        addr0 <= 4'd14;
        #(0*1s);
        web0 <= 1'd1;
        #(0*1s);
        #(1e-09*1s);
        clk0 <= 1'd1;
        #(0*1s);
        #(5e-09*1s);
        addr0 <= 4'd0;
        #(0*1s);
        web0 <= 1'd1;
        #(0*1s);
        clk0 <= 1'd0;
        #(0*1s);
        #(4e-09*1s);
        if (!(dout0 === 8'd208)) begin
            $error("Failed on action=253 checking port dout0 with traceback /Users/sgherbst/Dropbox/LaptopSync/Stanford/Research/Code/fault_experiments/sram/sram.py:70.  Expected %x, got %x.", 8'd208, dout0);
        end
        addr0 <= 4'd8;
        #(0*1s);
        web0 <= 1'd1;
        #(0*1s);
        #(1e-09*1s);
        clk0 <= 1'd1;
        #(0*1s);
        #(5e-09*1s);
        addr0 <= 4'd0;
        #(0*1s);
        web0 <= 1'd1;
        #(0*1s);
        clk0 <= 1'd0;
        #(0*1s);
        #(4e-09*1s);
        if (!(dout0 === 8'd155)) begin
            $error("Failed on action=263 checking port dout0 with traceback /Users/sgherbst/Dropbox/LaptopSync/Stanford/Research/Code/fault_experiments/sram/sram.py:70.  Expected %x, got %x.", 8'd155, dout0);
        end
        addr0 <= 4'd10;
        #(0*1s);
        web0 <= 1'd1;
        #(0*1s);
        #(1e-09*1s);
        clk0 <= 1'd1;
        #(0*1s);
        #(5e-09*1s);
        addr0 <= 4'd0;
        #(0*1s);
        web0 <= 1'd1;
        #(0*1s);
        clk0 <= 1'd0;
        #(0*1s);
        #(4e-09*1s);
        if (!(dout0 === 8'd121)) begin
            $error("Failed on action=273 checking port dout0 with traceback /Users/sgherbst/Dropbox/LaptopSync/Stanford/Research/Code/fault_experiments/sram/sram.py:70.  Expected %x, got %x.", 8'd121, dout0);
        end
        addr0 <= 4'd1;
        #(0*1s);
        web0 <= 1'd1;
        #(0*1s);
        #(1e-09*1s);
        clk0 <= 1'd1;
        #(0*1s);
        #(5e-09*1s);
        addr0 <= 4'd0;
        #(0*1s);
        web0 <= 1'd1;
        #(0*1s);
        clk0 <= 1'd0;
        #(0*1s);
        #(4e-09*1s);
        if (!(dout0 === 8'd201)) begin
            $error("Failed on action=283 checking port dout0 with traceback /Users/sgherbst/Dropbox/LaptopSync/Stanford/Research/Code/fault_experiments/sram/sram.py:70.  Expected %x, got %x.", 8'd201, dout0);
        end
        addr0 <= 4'd13;
        #(0*1s);
        web0 <= 1'd1;
        #(0*1s);
        #(1e-09*1s);
        clk0 <= 1'd1;
        #(0*1s);
        #(5e-09*1s);
        addr0 <= 4'd0;
        #(0*1s);
        web0 <= 1'd1;
        #(0*1s);
        clk0 <= 1'd0;
        #(0*1s);
        #(4e-09*1s);
        if (!(dout0 === 8'd144)) begin
            $error("Failed on action=293 checking port dout0 with traceback /Users/sgherbst/Dropbox/LaptopSync/Stanford/Research/Code/fault_experiments/sram/sram.py:70.  Expected %x, got %x.", 8'd144, dout0);
        end
        addr0 <= 4'd0;
        #(0*1s);
        web0 <= 1'd1;
        #(0*1s);
        #(1e-09*1s);
        clk0 <= 1'd1;
        #(0*1s);
        #(5e-09*1s);
        addr0 <= 4'd0;
        #(0*1s);
        web0 <= 1'd1;
        #(0*1s);
        clk0 <= 1'd0;
        #(0*1s);
        #(4e-09*1s);
        if (!(dout0 === 8'd64)) begin
            $error("Failed on action=303 checking port dout0 with traceback /Users/sgherbst/Dropbox/LaptopSync/Stanford/Research/Code/fault_experiments/sram/sram.py:70.  Expected %x, got %x.", 8'd64, dout0);
        end
        addr0 <= 4'd3;
        #(0*1s);
        web0 <= 1'd1;
        #(0*1s);
        #(1e-09*1s);
        clk0 <= 1'd1;
        #(0*1s);
        #(5e-09*1s);
        addr0 <= 4'd0;
        #(0*1s);
        web0 <= 1'd1;
        #(0*1s);
        clk0 <= 1'd0;
        #(0*1s);
        #(4e-09*1s);
        if (!(dout0 === 8'd217)) begin
            $error("Failed on action=313 checking port dout0 with traceback /Users/sgherbst/Dropbox/LaptopSync/Stanford/Research/Code/fault_experiments/sram/sram.py:70.  Expected %x, got %x.", 8'd217, dout0);
        end
        addr0 <= 4'd5;
        #(0*1s);
        web0 <= 1'd1;
        #(0*1s);
        #(1e-09*1s);
        clk0 <= 1'd1;
        #(0*1s);
        #(5e-09*1s);
        addr0 <= 4'd0;
        #(0*1s);
        web0 <= 1'd1;
        #(0*1s);
        clk0 <= 1'd0;
        #(0*1s);
        #(4e-09*1s);
        if (!(dout0 === 8'd98)) begin
            $error("Failed on action=323 checking port dout0 with traceback /Users/sgherbst/Dropbox/LaptopSync/Stanford/Research/Code/fault_experiments/sram/sram.py:70.  Expected %x, got %x.", 8'd98, dout0);
        end
        addr0 <= 4'd12;
        #(0*1s);
        web0 <= 1'd1;
        #(0*1s);
        #(1e-09*1s);
        clk0 <= 1'd1;
        #(0*1s);
        #(5e-09*1s);
        addr0 <= 4'd0;
        #(0*1s);
        web0 <= 1'd1;
        #(0*1s);
        clk0 <= 1'd0;
        #(0*1s);
        #(4e-09*1s);
        if (!(dout0 === 8'd119)) begin
            $error("Failed on action=333 checking port dout0 with traceback /Users/sgherbst/Dropbox/LaptopSync/Stanford/Research/Code/fault_experiments/sram/sram.py:70.  Expected %x, got %x.", 8'd119, dout0);
        end
        addr0 <= 4'd4;
        #(0*1s);
        web0 <= 1'd1;
        #(0*1s);
        #(1e-09*1s);
        clk0 <= 1'd1;
        #(0*1s);
        #(5e-09*1s);
        addr0 <= 4'd0;
        #(0*1s);
        web0 <= 1'd1;
        #(0*1s);
        clk0 <= 1'd0;
        #(0*1s);
        #(4e-09*1s);
        if (!(dout0 === 8'd125)) begin
            $error("Failed on action=343 checking port dout0 with traceback /Users/sgherbst/Dropbox/LaptopSync/Stanford/Research/Code/fault_experiments/sram/sram.py:70.  Expected %x, got %x.", 8'd125, dout0);
        end
        #20 $finish;
    end

endmodule

sram/build/waveforms.vcd
$date
	Tue Jan 14 18:23:42 2020
$end
$version
	Icarus Verilog
$end
$timescale
	1ns
$end
$scope module sram_8_16_scn4m_subm_tb $end
$scope module dut $end
$var wire 4 ! addr0 [3:0] $end
$var wire 1 " clk0 $end
$var wire 1 # csb0 $end
$var wire 8 $ din0 [7:0] $end
$var wire 1 % web0 $end
$var reg 4 & addr0_reg [3:0] $end
$var reg 1 ' csb0_reg $end
$var reg 8 ( din0_reg [7:0] $end
$var reg 8 ) dout0 [7:0] $end
$var reg 1 * web0_reg $end
$scope begin MEM_READ0 $end
$upscope $end
$scope begin MEM_WRITE0 $end
$upscope $end
$upscope $end
$upscope $end
$enddefinitions $end
#0
$dumpvars
x*
bx )
bx (
x'
bx &
0%
b0 $
0#
0"
b0 !
$end
#25
1%
#50
0%
b11 !
b11011001 $
#51
b11011001 (
b11 &
0*
0'
1"
#56
0"
1%
b0 !
b0 $
#60
0%
b1101 !
b10010000 $
#61
b10010000 (
b1101 &
1"
#66
0"
1%
b0 !
b0 $
#70
0%
b100 !
b1111101 $
#71
b1111101 (
b100 &
1"
#76
0"
1%
b0 !
b0 $
#80
0%
b1000 !
b10011011 $
#81
b10011011 (
b1000 &
1"
#86
0"
1%
b0 !
b0 $
#90
0%
b1 !
b11001001 $
#91
b11001001 (
b1 &
1"
#96
0"
1%
b0 !
b0 $
#100
0%
b1001 !
b1011000 $
#101
b1011000 (
b1001 &
1"
#106
0"
1%
b0 !
b0 $
#110
0%
b1010 !
b1111001 $
#111
b1111001 (
b1010 &
1"
#116
0"
1%
b0 !
b0 $
#120
0%
b10 !
b11000101 $
#121
b11000101 (
b10 &
1"
#126
0"
1%
b0 !
b0 $
#130
0%
b101 !
b1100010 $
#131
b1100010 (
b101 &
1"
#136
0"
1%
b0 !
b0 $
#140
0%
b1110 !
b11010000 $
#141
b11010000 (
b1110 &
1"
#146
0"
1%
b0 !
b0 $
#150
0%
b111 !
b11100100 $
#151
b11100100 (
b111 &
1"
#156
0"
1%
b0 !
b0 $
#160
0%
b110 !
b101011 $
#161
b101011 (
b110 &
1"
#166
0"
1%
b0 !
b0 $
#170
0%
b1000000 $
#171
b1000000 (
b0 &
1"
#176
0"
1%
b0 $
#180
0%
b1100 !
b1110111 $
#181
b1110111 (
b1100 &
1"
#186
0"
1%
b0 !
b0 $
#190
0%
b1111 !
b11111000 $
#191
b11111000 (
b1111 &
1"
#196
0"
1%
b0 !
b0 $
#200
0%
b1011 !
b11111001 $
#201
b11111001 (
b1011 &
1"
#206
0"
1%
b0 !
b0 $
#210
b1001 !
#211
b0 (
b1001 &
1*
1"
#216
0"
b0 !
#219
b1011000 )
#220
b111 !
#221
bx )
b111 &
1"
#226
0"
b0 !
#229
b11100100 )
#230
b1111 !
#231
bx )
b1111 &
1"
#236
0"
b0 !
#239
b11111000 )
#240
b1011 !
#241
bx )
b1011 &
1"
#246
0"
b0 !
#249
b11111001 )
#250
b110 !
#251
bx )
b110 &
1"
#256
0"
b0 !
#259
b101011 )
#260
b10 !
#261
bx )
b10 &
1"
#266
0"
b0 !
#269
b11000101 )
#270
b1110 !
#271
bx )
b1110 &
1"
#276
0"
b0 !
#279
b11010000 )
#280
b1000 !
#281
bx )
b1000 &
1"
#286
0"
b0 !
#289
b10011011 )
#290
b1010 !
#291
bx )
b1010 &
1"
#296
0"
b0 !
#299
b1111001 )
#300
b1 !
#301
bx )
b1 &
1"
#306
0"
b0 !
#309
b11001001 )
#310
b1101 !
#311
bx )
b1101 &
1"
#316
0"
b0 !
#319
b10010000 )
#321
bx )
b0 &
1"
#326
0"
#329
b1000000 )
#330
b11 !
#331
bx )
b11 &
1"
#336
0"
b0 !
#339
b11011001 )
#340
b101 !
#341
bx )
b101 &
1"
#346
0"
b0 !
#349
b1100010 )
#350
b1100 !
#351
bx )
b1100 &
1"
#356
0"
b0 !
#359
b1110111 )
#360
b100 !
#361
bx )
b100 &
1"
#366
0"
b0 !
#369
b1111101 )
